spindata/__init__.py
spindata/gamma.py
spindata/polarization.py
spindata/quadrupolemoment.py
spindata/spin.py
spindata-1.12.dist-info/METADATA
spindata-1.12.dist-info/WHEEL
spindata-1.12.dist-info/top_level.txt
spindata-1.12.dist-info/RECORD
