Metadata-Version: 2.1
Name: spindata
Version: 1.12
Summary: Gyromagnetic ratios, spin, and quadrupole moments (where applicable) of all elements and the electron.
Home-page: http://github.com/bennomeier/spindata
Author: Benno Meier
Author-email: meier.benno@gmail.com
License: MIT
Keywords: NMR spin nuclear magnetic resonance gyromagnetic ratio
Platform: UNKNOWN
Classifier: License :: OSI Approved :: MIT License
Classifier: Programming Language :: Python
Classifier: Topic :: Scientific/Engineering :: Physics
Requires-Dist: numpy
Requires-Dist: scipy
